zmote/__init__.py
zmote/connector.py
zmote/connector_test.py
zmote/discoverer.py
zmote/discoverer_test.py
zmote-2017.7.data/data/README.md
zmote-2017.7.dist-info/DESCRIPTION.rst
zmote-2017.7.dist-info/METADATA
zmote-2017.7.dist-info/RECORD
zmote-2017.7.dist-info/WHEEL
zmote-2017.7.dist-info/metadata.json
zmote-2017.7.dist-info/top_level.txt
