Metadata-Version: 2.0
Name: zmote
Version: 2017.7
Summary: Unofficial zmote.io interface
Home-page: https://github.com/initialed85/zmote
Author: Edward Beech
Author-email: initialed85@gmail.com
License: MIT
Keywords: sample setuptools development
Platform: UNKNOWN
Classifier: Development Status :: 3 - Alpha
Classifier: Intended Audience :: Developers
Classifier: Topic :: Software Development :: Libraries
Classifier: License :: OSI Approved :: MIT License
Classifier: Programming Language :: Python :: 2.7
Requires-Dist: requests (==2.18.4)
Provides-Extra: dev
Requires-Dist: check-manifest; extra == 'dev'
Provides-Extra: test
Requires-Dist: coverage; extra == 'test'
